{
  "source_file": "output\\결제2_res.json",
  "extracted_digits": [
    "2",
    "6",
    "8",
    "0",
    "9",
    "7",
    "3",
    "5",
    "4",
    "1"
  ],
  "dom_keys": [
    "key-100",
    "key-101",
    "key-102",
    "key-103",
    "key-104",
    "key-105",
    "key-106",
    "key-107",
    "key-108",
    "key-109"
  ],
  "digit_to_key_mapping": {
    "2": "key-100",
    "6": "key-101",
    "8": "key-102",
    "0": "key-103",
    "9": "key-104",
    "7": "key-105",
    "3": "key-106",
    "5": "key-107",
    "4": "key-108",
    "1": "key-109"
  }
}